Price_Uncertainty_HLCA/__init__.py
Price_Uncertainty_HLCA/ecoinvent_HS_commodity_mapping.py
Price_Uncertainty_HLCA/make_price_df.py
Price_Uncertainty_HLCA/match_BACI_price_data_to_ecoinvent.py
Price_Uncertainty_HLCA/price_variance_MC.py
Price_Uncertainty_HLCA/region_mapping.py
Price_Uncertainty_HLCA-0.1.dist-info/LICENSE
Price_Uncertainty_HLCA-0.1.dist-info/METADATA
Price_Uncertainty_HLCA-0.1.dist-info/WHEEL
Price_Uncertainty_HLCA-0.1.dist-info/top_level.txt
Price_Uncertainty_HLCA-0.1.dist-info/RECORD
