Metadata-Version: 2.1
Name: Price-Uncertainty-HLCA
Version: 0.1
Summary: Arthur Jakobs
Home-page: https://github.com/jakobsarthur/Price_Uncertainty_HLCA
Author: Arthur Jakobs
Author-email: arthur.jakobs@indecol.uni-freiburg.de
License: BSD-3-Clause
Platform: UNKNOWN
Classifier: Intended Audience :: End Users/Desktop
Classifier: Intended Audience :: Developers
Classifier: Intended Audience :: Science/Research
Classifier: License :: OSI Approved :: BSD License
Classifier: Operating System :: MacOS :: MacOS X
Classifier: Operating System :: Microsoft :: Windows
Classifier: Operating System :: POSIX
Classifier: Programming Language :: Python
Classifier: Programming Language :: Python :: 3
Classifier: Programming Language :: Python :: 3.5
Classifier: Programming Language :: Python :: 3.6
Classifier: Programming Language :: Python :: 3.7
Classifier: Topic :: Scientific/Engineering :: Information Analysis
Classifier: Topic :: Scientific/Engineering :: Mathematics
Requires-Dist: appdirs
